subgatekit/__init__.py
subgatekit/client/__init__.py
subgatekit/client/base_client.py
subgatekit/client/client.py
subgatekit/client/deserializers.py
subgatekit/client/plan_client.py
subgatekit/client/serailizers.py
subgatekit/client/services.py
subgatekit/client/subscription_client.py
subgatekit/client/webhook_client.py
subgatekit/entities.py
subgatekit/enums.py
subgatekit/exceptions.py
subgatekit/factories.py
subgatekit/item_manager.py
subgatekit/utils.py
subgatekit/validators.py
subgatekit-0.2.0.dist-info/METADATA
subgatekit-0.2.0.dist-info/WHEEL
subgatekit-0.2.0.dist-info/RECORD
